[{
  "_id": {
    "$oid": "6382f1599c1eacccf07bb4b8"
  },
  "useId": {
    "$oid": "6382f12a9c1eacccf07bb4b3"
  },
  "tourId": {
    "$oid": "6381fbfa4e20980e892a727f"
  },
  "name": "Văn",
  "email": "van2@gmail.com",
  "phone": "0778988899",
  "address": "Cần Thơ",
  "adult": 1,
  "child": 1,
  "total": 6285000,
  "createdAt": {
    "$date": {
      "$numberLong": "1669525849207"
    }
  },
  "updatedAt": {
    "$date": {
      "$numberLong": "1669525849207"
    }
  },
  "__v": 0
},{
  "_id": {
    "$oid": "6382f1949c1eacccf07bb4bf"
  },
  "useId": {
    "$oid": "6382f12a9c1eacccf07bb4b3"
  },
  "tourId": {
    "$oid": "63819b962100b71c7d615fec"
  },
  "name": "Kahn",
  "email": "van2@gmail.com",
  "phone": "0111222333",
  "address": "Cần Thơ",
  "adult": 2,
  "child": 0,
  "total": 21980000,
  "createdAt": {
    "$date": {
      "$numberLong": "1669525908698"
    }
  },
  "updatedAt": {
    "$date": {
      "$numberLong": "1669525908698"
    }
  },
  "__v": 0
},{
  "_id": {
    "$oid": "6382f27f9c1eacccf07bb4d7"
  },
  "useId": {
    "$oid": "6382ec5d53ebd3bd9d489f81"
  },
  "tourId": {
    "$oid": "6381ff3c4e20980e892a7284"
  },
  "name": "Ng Khánh Văn",
  "email": "van@gmail.com",
  "phone": "0777665544",
  "address": "DT",
  "adult": 1,
  "child": 2,
  "total": 12980000,
  "createdAt": {
    "$date": {
      "$numberLong": "1669526143579"
    }
  },
  "updatedAt": {
    "$date": {
      "$numberLong": "1669526143579"
    }
  },
  "__v": 0
},{
  "_id": {
    "$oid": "6385836cf940caff6f1c159b"
  },
  "useId": {
    "$oid": "6382ec5d53ebd3bd9d489f81"
  },
  "tourId": {
    "$oid": "6381fbfa4e20980e892a727f"
  },
  "name": "Khánh Văn",
  "email": "van@gmail.com",
  "phone": "0777665544",
  "address": "Đồng Tháp",
  "adult": 2,
  "child": 1,
  "total": 10475000,
  "createdAt": {
    "$date": {
      "$numberLong": "1669694316969"
    }
  },
  "updatedAt": {
    "$date": {
      "$numberLong": "1669694316969"
    }
  },
  "__v": 0
},{
  "_id": {
    "$oid": "6385e2c94035332188f3e81a"
  },
  "useId": {
    "$oid": "6385e2a04035332188f3e815"
  },
  "tourId": {
    "$oid": "6385db9d4035332188f3e7b2"
  },
  "name": "Nguyễn Văn A",
  "email": "van3@gmail.com",
  "phone": "0778988899",
  "address": "Cần Thơ",
  "adult": 1,
  "child": 1,
  "total": 7635000,
  "createdAt": {
    "$date": {
      "$numberLong": "1669718729429"
    }
  },
  "updatedAt": {
    "$date": {
      "$numberLong": "1669718729429"
    }
  },
  "__v": 0
},{
  "_id": {
    "$oid": "6385e32d4035332188f3e824"
  },
  "useId": {
    "$oid": "6385e2f74035332188f3e81f"
  },
  "tourId": {
    "$oid": "6385d7d14035332188f3e7a2"
  },
  "name": "Phạm Thị B",
  "email": "van4@gmail.com",
  "phone": "0909444777",
  "address": "Cần Thơ",
  "adult": 1,
  "child": 0,
  "total": 82000000,
  "createdAt": {
    "$date": {
      "$numberLong": "1669718829649"
    }
  },
  "updatedAt": {
    "$date": {
      "$numberLong": "1669718829649"
    }
  },
  "__v": 0
},{
  "_id": {
    "$oid": "6385e3ac4035332188f3e831"
  },
  "useId": {
    "$oid": "6385e3794035332188f3e82c"
  },
  "tourId": {
    "$oid": "6385d6984035332188f3e79c"
  },
  "name": "Lê Trần Nguyễn",
  "email": "van1@gmail.com",
  "phone": "0123456654",
  "address": "Đồng Tháp",
  "adult": 3,
  "child": 3,
  "total": 116550000,
  "createdAt": {
    "$date": {
      "$numberLong": "1669718956785"
    }
  },
  "updatedAt": {
    "$date": {
      "$numberLong": "1669718956785"
    }
  },
  "__v": 0
},{
  "_id": {
    "$oid": "6385e55f4035332188f3e84b"
  },
  "useId": {
    "$oid": "6385e2a04035332188f3e815"
  },
  "tourId": {
    "$oid": "6385db1d4035332188f3e7af"
  },
  "name": "Nguyễn Văn A",
  "email": "van3@gmail.com",
  "phone": "078727887",
  "address": "Sóc Trăng",
  "adult": 2,
  "child": 1,
  "total": 11225000,
  "createdAt": {
    "$date": {
      "$numberLong": "1669719391562"
    }
  },
  "updatedAt": {
    "$date": {
      "$numberLong": "1669719391562"
    }
  },
  "__v": 0
},{
  "_id": {
    "$oid": "6385e69e4035332188f3e85e"
  },
  "useId": {
    "$oid": "6382ec5d53ebd3bd9d489f81"
  },
  "tourId": {
    "$oid": "6385d7224035332188f3e79f"
  },
  "name": "Khánh Văn",
  "email": "van@gmail.com",
  "phone": "0777665546",
  "address": "Cần Thơ",
  "adult": 1,
  "child": 1,
  "total": 52020000,
  "createdAt": {
    "$date": {
      "$numberLong": "1669719710556"
    }
  },
  "updatedAt": {
    "$date": {
      "$numberLong": "1669719710556"
    }
  },
  "__v": 0
},{
  "_id": {
    "$oid": "638657874035332188f3e88a"
  },
  "useId": {
    "$oid": "6382ec5d53ebd3bd9d489f81"
  },
  "tourId": {
    "$oid": "6381fbfa4e20980e892a727f"
  },
  "name": "Khánh Văn",
  "email": "van@gmail.com",
  "phone": "0777665546",
  "address": "Cần Thơ",
  "adult": 2,
  "child": 1,
  "total": 10475000,
  "createdAt": {
    "$date": {
      "$numberLong": "1669748615541"
    }
  },
  "updatedAt": {
    "$date": {
      "$numberLong": "1669748615541"
    }
  },
  "__v": 0
},{
  "_id": {
    "$oid": "638657ca4035332188f3e891"
  },
  "useId": {
    "$oid": "6382ec5d53ebd3bd9d489f81"
  },
  "tourId": {
    "$oid": "6385db9d4035332188f3e7b2"
  },
  "name": "Khánh Văn",
  "email": "van@gmail.com",
  "phone": "0777665546",
  "address": "Cnầ thơ",
  "adult": 1,
  "child": 0,
  "total": 5090000,
  "createdAt": {
    "$date": {
      "$numberLong": "1669748682458"
    }
  },
  "updatedAt": {
    "$date": {
      "$numberLong": "1669748682458"
    }
  },
  "__v": 0
}]